szu_autoconnect/__init__.py
szu_autoconnect/open_ui.py
szu_autoconnect/run.py
szu_autoconnect/core/__init__.py
szu_autoconnect/core/auto.py
szu_autoconnect/core/ui.py
szu_autoconnect-1.0.4.dist-info/LICENSE
szu_autoconnect-1.0.4.dist-info/METADATA
szu_autoconnect-1.0.4.dist-info/WHEEL
szu_autoconnect-1.0.4.dist-info/top_level.txt
szu_autoconnect-1.0.4.dist-info/RECORD
