Metadata-Version: 2.1
Name: szu-autoconnect
Version: 1.0.4
Summary: A simple way to get different DEXs abis for block chains.
Home-page: https://github.com/ackness/szu-autoconnect
Author: Yong
Author-email: ackness8@gmail.com
License: MIT
Keywords: drcom,auto,SZU
Platform: UNKNOWN
License-File: LICENSE
Requires-Dist: PySimpleGUI
Requires-Dist: apscheduler
Requires-Dist: loguru
Requires-Dist: retrying
Requires-Dist: requests
